src/__init__.py
src/cli.py
src/config.py
src/encryption.py
src/diary/__init__.py
src/diary/cli.py
src/diary/config.py
src/diary/encryption.py
deary_encrypted-0.1.dist-info/METADATA
deary_encrypted-0.1.dist-info/WHEEL
deary_encrypted-0.1.dist-info/entry_points.txt
deary_encrypted-0.1.dist-info/top_level.txt
deary_encrypted-0.1.dist-info/RECORD
