Metadata-Version: 2.1
Name: deary_encrypted
Version: 0.1
Author: Varinder
Author-email: varinder2021singh@gmail.com
Classifier: Programming Language :: Python :: 3.8
Classifier: Operating System :: OS Independent
Requires-Python: >=3.8
Requires-Dist: click >=8.0.1
Requires-Dist: cryptography >=3.3.2
Requires-Dist: python-dotenv <=0.19,>=0.18
